duck_agents/__init__.py
duck_agents/base_agent.py
duck_agents/llm/__init__.py
duck_agents/llm/gemini_session_factory.py
duck_agents/llm/ollama_session_factory.py
duck_agents/llm/session_factory.py
duck_agents/llm/token_count_handler.py
duck_agents-0.1.10.dist-info/METADATA
duck_agents-0.1.10.dist-info/WHEEL
duck_agents-0.1.10.dist-info/RECORD
